repository_miner/__init__.py
repository_miner/data_typing.py
repository_miner/exceptions.py
repository_miner/git.py
repository_miner/helper.py
repository_miner/miner.py
repository_miner/py.typed
repository_miner/utility.py
repominer_gdeluisi-1.5.0.dist-info/METADATA
repominer_gdeluisi-1.5.0.dist-info/WHEEL
repominer_gdeluisi-1.5.0.dist-info/licenses/LICENSE
repominer_gdeluisi-1.5.0.dist-info/RECORD
