Metadata-Version: 2.4
Name: repominer-GDeLuisi
Version: 1.5.0
Summary: Tool for mining git managed repositories
Author: Gerardo De Luisi
License-File: LICENSE
Keywords: git,miner,projects
Classifier: License :: OSI Approved :: GNU General Public License v3 or later (GPLv3+)
Classifier: Operating System :: OS Independent
Classifier: Programming Language :: Python :: 3.10
Classifier: Programming Language :: Python :: 3.11
Classifier: Programming Language :: Python :: 3.12
Classifier: Programming Language :: Python :: 3.13
Requires-Python: >=3.10
